imgori/__init__.py
imgori/cli.py
imgori/imgori.py
imgori/optim.py
imgori/types.py
imgori/commands/__init__.py
imgori/commands/train.py
imgori/datasets/__init__.py
imgori/datasets/imgori.py
imgori/datasets/mnist.py
imgori/datasets/utils.py
imgori/datasets/blur/__init__.py
imgori/datasets/blur/cuhk.py
imgori/models/__init__.py
imgori/models/imgori_mobilenet_v3_small.pth
imgori/nn/__init__.py
imgori/nn/efficientnet.py
imgori/nn/lenet.py
imgori/nn/mobilenet_v3.py
imgori/trainers/__init__.py
imgori/trainers/imgori.py
imgori/trainers/mnist.py
imgori/trainers/trainer.py
imgori/utils/__init__.py
imgori/utils/hub.py
imgori/utils/timeit.py
imgori/utils/utils.py
imgori-0.7.0.dist-info/METADATA
imgori-0.7.0.dist-info/WHEEL
imgori-0.7.0.dist-info/entry_points.txt
imgori-0.7.0.dist-info/RECORD
